pyrdf_prefix/__init__.py
pyrdf_prefix/namespace.py
pyrdf_prefix/predefined/_AS.py
pyrdf_prefix/predefined/_BRICK.py
pyrdf_prefix/predefined/_CC.py
pyrdf_prefix/predefined/_CSVW.py
pyrdf_prefix/predefined/_CTAG.py
pyrdf_prefix/predefined/_DC.py
pyrdf_prefix/predefined/_DC11.py
pyrdf_prefix/predefined/_DCAM.py
pyrdf_prefix/predefined/_DCAT.py
pyrdf_prefix/predefined/_DCMITYPE.py
pyrdf_prefix/predefined/_DCTERMS.py
pyrdf_prefix/predefined/_DOAP.py
pyrdf_prefix/predefined/_DQV.py
pyrdf_prefix/predefined/_DUV.py
pyrdf_prefix/predefined/_FOAF.py
pyrdf_prefix/predefined/_GEO.py
pyrdf_prefix/predefined/_GR.py
pyrdf_prefix/predefined/_GRDDL.py
pyrdf_prefix/predefined/_ICAL.py
pyrdf_prefix/predefined/_JSONLD.py
pyrdf_prefix/predefined/_LDP.py
pyrdf_prefix/predefined/_MA.py
pyrdf_prefix/predefined/_OA.py
pyrdf_prefix/predefined/_ODRL.py
pyrdf_prefix/predefined/_OG.py
pyrdf_prefix/predefined/_ORG.py
pyrdf_prefix/predefined/_OWL.py
pyrdf_prefix/predefined/_PROF.py
pyrdf_prefix/predefined/_PROV.py
pyrdf_prefix/predefined/_QB.py
pyrdf_prefix/predefined/_RDF.py
pyrdf_prefix/predefined/_RDFA.py
pyrdf_prefix/predefined/_RDFS.py
pyrdf_prefix/predefined/_REV.py
pyrdf_prefix/predefined/_RIF.py
pyrdf_prefix/predefined/_RR.py
pyrdf_prefix/predefined/_SCHEMA.py
pyrdf_prefix/predefined/_SD.py
pyrdf_prefix/predefined/_SH.py
pyrdf_prefix/predefined/_SIOC.py
pyrdf_prefix/predefined/_SKOS.py
pyrdf_prefix/predefined/_SKOSXL.py
pyrdf_prefix/predefined/_SOSA.py
pyrdf_prefix/predefined/_SSN.py
pyrdf_prefix/predefined/_TIME.py
pyrdf_prefix/predefined/_V.py
pyrdf_prefix/predefined/_VANN.py
pyrdf_prefix/predefined/_VCARD.py
pyrdf_prefix/predefined/_VOID.py
pyrdf_prefix/predefined/_WDR.py
pyrdf_prefix/predefined/_WDRS.py
pyrdf_prefix/predefined/_WGS.py
pyrdf_prefix/predefined/_XHV.py
pyrdf_prefix/predefined/_XML.py
pyrdf_prefix/predefined/_XSD.py
pyrdf_prefix/predefined/__init__.py
pyrdf_prefix-0.2.1.dist-info/METADATA
pyrdf_prefix-0.2.1.dist-info/WHEEL
pyrdf_prefix-0.2.1.dist-info/RECORD
