Metadata-Version: 2.3
Name: pyrdf-prefix
Version: 0.2.1
Summary: Easily access common RDF vocabularies and your own custom namespaces, for usage with pyoxigraph
Requires-Python: >=3.10
Requires-Dist: pyoxigraph>=0.4.0
